setup.py
scheduling/__init__.py
scheduling/graph.py
scheduling/scheduler.py
scheduling/tasks.py
scheduling.egg-info/PKG-INFO
scheduling.egg-info/SOURCES.txt
scheduling.egg-info/dependency_links.txt
scheduling.egg-info/top_level.txt