Metadata-Version: 1.0
Name: scheduling
Version: 0.0.1
Summary: Task scheduling library
Home-page: https://github.com/alevinval/scheduling
Author: Àlex Vinyals
Author-email: alevinval@gmail.com
License: UNKNOWN
Keywords: Graphs,Scheduling
Platform: UNKNOWN
